aivp/__init__.py
aivp/aivp.py
aivp-0.2.1.dist-info/LICENSE
aivp-0.2.1.dist-info/METADATA
aivp-0.2.1.dist-info/WHEEL
aivp-0.2.1.dist-info/top_level.txt
aivp-0.2.1.dist-info/RECORD
